brynq_sdk_datev/__init__.py
brynq_sdk_datev/hr_exchange/__init__.py
brynq_sdk_datev/hr_exchange/absences.py
brynq_sdk_datev/hr_exchange/base.py
brynq_sdk_datev/hr_exchange/employees.py
brynq_sdk_datev/hr_exchange/employment_periods.py
brynq_sdk_datev/hr_exchange/gross_payments.py
brynq_sdk_datev/hr_exchange/hourly_wages.py
brynq_sdk_datev/hr_exchange/individual_data.py
brynq_sdk_datev/hr_exchange/monthly_records.py
brynq_sdk_datev/hr_exchange/organization.py
brynq_sdk_datev/hr_exchange/schemas/__init__.py
brynq_sdk_datev/hr_exchange/schemas/_api.py
brynq_sdk_datev/hr_exchange/schemas/_enums.py
brynq_sdk_datev/hr_exchange/schemas/absences.py
brynq_sdk_datev/hr_exchange/schemas/employee.py
brynq_sdk_datev/hr_exchange/schemas/financial.py
brynq_sdk_datev/hr_exchange/schemas/individual_data.py
brynq_sdk_datev/hr_exchange/schemas/monthly_records.py
brynq_sdk_datev/hr_exchange/schemas/organizational.py
brynq_sdk_datev/hr_exchange/schemas/tax_insurance.py
brynq_sdk_datev/lodas/__init__.py
brynq_sdk_datev/lodas/datev_lodas.py
brynq_sdk_datev/lodas/datev_lodas_mapping.py
brynq_sdk_datev/lodas/datev_mapping.py
brynq_sdk_datev/lohn_und_gehalt/__init__.py
brynq_sdk_datev/lohn_und_gehalt/account.py
brynq_sdk_datev/lohn_und_gehalt/accountable_employees.py
brynq_sdk_datev/lohn_und_gehalt/activity.py
brynq_sdk_datev/lohn_und_gehalt/address.py
brynq_sdk_datev/lohn_und_gehalt/base.py
brynq_sdk_datev/lohn_und_gehalt/clients.py
brynq_sdk_datev/lohn_und_gehalt/cost_centers.py
brynq_sdk_datev/lohn_und_gehalt/cost_units.py
brynq_sdk_datev/lohn_und_gehalt/departments.py
brynq_sdk_datev/lohn_und_gehalt/disability.py
brynq_sdk_datev/lohn_und_gehalt/employees.py
brynq_sdk_datev/lohn_und_gehalt/employment_periods.py
brynq_sdk_datev/lohn_und_gehalt/financial_accounting.py
brynq_sdk_datev/lohn_und_gehalt/gross_payments.py
brynq_sdk_datev/lohn_und_gehalt/hourly_wages.py
brynq_sdk_datev/lohn_und_gehalt/individual_data.py
brynq_sdk_datev/lohn_und_gehalt/month_records.py
brynq_sdk_datev-3.5.0.dist-info/METADATA
brynq_sdk_datev-3.5.0.dist-info/WHEEL
brynq_sdk_datev-3.5.0.dist-info/top_level.txt
brynq_sdk_datev-3.5.0.dist-info/RECORD
