Metadata-Version: 2.4
Name: brynq_sdk_datev
Version: 3.5.0
Summary: Datev wrapper from Salure
Author: D&A Salure
Author-email: support@salureconnnect.com
License: BrynQ License
Requires-Dist: brynq-sdk-brynq<5,>=4
Requires-Dist: brynq-sdk-functions>=2
Requires-Dist: pandas<=3,>=1
Dynamic: author
Dynamic: author-email
Dynamic: description
Dynamic: license
Dynamic: requires-dist
Dynamic: summary
